katsdpservices/__init__.py
katsdpservices/aiomonitor.py
katsdpservices/argparse.py
katsdpservices/interfaces.py
katsdpservices/logging.py
katsdpservices/restart.py
katsdpservices-1.4.dist-info/LICENSE
katsdpservices-1.4.dist-info/METADATA
katsdpservices-1.4.dist-info/WHEEL
katsdpservices-1.4.dist-info/top_level.txt
katsdpservices-1.4.dist-info/RECORD
