Metadata-Version: 2.1
Name: katsdpservices
Version: 1.4
Summary: Common code used by services that make up the MeerKAT Science Data Processor, such as a common logging setup
Home-page: https://github.com/ska-sa/katsdpservices
Author: MeerKAT SDP Team
Author-email: sdpdev+katsdpservices@sarao.ac.za
License: Modified BSD
Classifier: Development Status :: 5 - Production/Stable
Classifier: Intended Audience :: Developers
Classifier: License :: OSI Approved :: BSD License
Classifier: Operating System :: OS Independent
Classifier: Programming Language :: Python
Classifier: Programming Language :: Python :: 3
Classifier: Topic :: Scientific/Engineering :: Astronomy
Requires-Python: >=3.8
License-File: LICENSE
Requires-Dist: netifaces
Requires-Dist: pygelf >=0.3.6
Provides-Extra: aiomonitor
Requires-Dist: aiomonitor ; extra == 'aiomonitor'
Provides-Extra: argparse
Requires-Dist: katsdptelstate ; extra == 'argparse'
Provides-Extra: test
Requires-Dist: aiomonitor ; extra == 'test'
Requires-Dist: katsdptelstate ; extra == 'test'
Requires-Dist: pytest ; extra == 'test'
